{"roomName":"pub","roomStarted":1525092019687,"chat":[{"room":"pub","from":"marko","text":"hi there how's it going? https://tedideas.files.wordpress.com/2017/06/web_ready_el-castillo-female-hand.jpg","timeStamp":1524766555826},{"room":"pub","from":"john 5","text":"hi there, cool app!","timeStamp":1525100553371},{"room":"pub","from":"john 5","text":"lets test","timeStamp":1525100885464},{"room":"pub","from":"hans zimm","text":"I like it too!","timeStamp":1525101625464},{"from":"hacker","text":"hack hack","timeStamp":1525354437172}]}